Workbook

Sheet Lojas
A1: loja_id | B1: nome_loja | C1: cidade | D1: estado | E1: regiao
A2: L01 | B2: Loja São Paulo | C2: São Paulo | D2: SP | E2: Sudeste
A3: L02 | B3: Loja Rio de Janeiro | C3: Rio de Janeiro | D3: RJ | E3: Sudeste
A4: L03 | B4: Loja Belo Horizonte | C4: Belo Horizonte | D4: MG | E4: Sudeste
A5: L04 | B5: Loja Vitória | C5: Vitória | D5: ES | E5: Sudeste
A6: L05 | B6: Loja Curitiba | C6: Curitiba | D6: PR | E6: Sul
A7: L06 | B7: Loja Porto Alegre | C7: Porto Alegre | D7: RS | E7: Sul
A8: L07 | B8: Loja Florianópolis | C8: Florianópolis | D8: SC | E8: Sul
A9: L08 | B9: Loja Salvador | C9: Salvador | D9: BA | E9: Nordeste
A10: L09 | B10: Loja Recife | C10: Recife | D10: PE | E10: Nordeste
A11: L10 | B11: Loja Fortaleza | C11: Fortaleza | D11: CE | E11: Nordeste

Sheet Vendedores
A1: vendedor_id | B1: nome_vendedor | C1: loja_id | D1: nome_loja | E1: regiao
A2: V001 | B2: Hugo Silva | C2: L01 | D2: =INDEX(Lojas!$B$2:$B$11,MATCH(C2,Lojas!$A$2:$A$11,0)) -> Loja São Paulo | E2: =INDEX(Lojas!$E$2:$E$11,MATCH(C2,Lojas!$A$2:$A$11,0)) -> Sudeste
A3: V002 | B3: Rafael Almeida | C3: L01 | D3: =INDEX(Lojas!$B$2:$B$11,MATCH(C3,Lojas!$A$2:$A$11,0)) -> Loja São Paulo | E3: =INDEX(Lojas!$E$2:$E$11,MATCH(C3,Lojas!$A$2:$A$11,0)) -> Sudeste
A4: V003 | B4: Olívia Pereira | C4: L01 | D4: =INDEX(Lojas!$B$2:$B$11,MATCH(C4,Lojas!$A$2:$A$11,0)) -> Loja São Paulo | E4: =INDEX(Lojas!$E$2:$E$11,MATCH(C4,Lojas!$A$2:$A$11,0)) -> Sudeste
A5: V004 | B5: Gabriela Alves | C5: L01 | D5: =INDEX(Lojas!$B$2:$B$11,MATCH(C5,Lojas!$A$2:$A$11,0)) -> Loja São Paulo | E5: =INDEX(Lojas!$E$2:$E$11,MATCH(C5,Lojas!$A$2:$A$11,0)) -> Sudeste
A6: V005 | B6: Fabio Monteiro | C6: L01 | D6: =INDEX(Lojas!$B$2:$B$11,MATCH(C6,Lojas!$A$2:$A$11,0)) -> Loja São Paulo | E6: =INDEX(Lojas!$E$2:$E$11,MATCH(C6,Lojas!$A$2:$A$11,0)) -> Sudeste
A7: V006 | B7: Bernardo Souza | C7: L01 | D7: =INDEX(Lojas!$B$2:$B$11,MATCH(C7,Lojas!$A$2:$A$11,0)) -> Loja São Paulo | E7: =INDEX(Lojas!$E$2:$E$11,MATCH(C7,Lojas!$A$2:$A$11,0)) -> Sudeste
A8: V007 | B8: Bruno Oliveira | C8: L01 | D8: =INDEX(Lojas!$B$2:$B$11,MATCH(C8,Lojas!$A$2:$A$11,0)) -> Loja São Paulo | E8: =INDEX(Lojas!$E$2:$E$11,MATCH(C8,Lojas!$A$2:$A$11,0)) -> Sudeste
A9: V008 | B9: Nelson Almeida | C9: L01 | D9: =INDEX(Lojas!$B$2:$B$11,MATCH(C9,Lojas!$A$2:$A$11,0)) -> Loja São Paulo | E9: =INDEX(Lojas!$E$2:$E$11,MATCH(C9,Lojas!$A$2:$A$11,0)) -> Sudeste
A10: V009 | B10: Giovana Barbosa | C10: L01 | D10: =INDEX(Lojas!$B$2:$B$11,MATCH(C10,Lojas!$A$2:$A$11,0)) -> Loja São Paulo | E10: =INDEX(Lojas!$E$2:$E$11,MATCH(C10,Lojas!$A$2:$A$11,0)) -> Sudeste
A11: V010 | B11: Bruno Alves | C11: L01 | D11: =INDEX(Lojas!$B$2:$B$11,MATCH(C11,Lojas!$A$2:$A$11,0)) -> Loja São Paulo | E11: =INDEX(Lojas!$E$2:$E$11,MATCH(C11,Lojas!$A$2:$A$11,0)) -> Sudeste
A12: V011 | B12: Mariana Alves | C12: L02 | D12: =INDEX(Lojas!$B$2:$B$11,MATCH(C12,Lojas!$A$2:$A$11,0)) -> Loja Rio de Janeiro | E12: =INDEX(Lojas!$E$2:$E$11,MATCH(C12,Lojas!$A$2:$A$11,0)) -> Sudeste
A13: V012 | B13: Aline Almeida | C13: L02 | D13: =INDEX(Lojas!$B$2:$B$11,MATCH(C13,Lojas!$A$2:$A$11,0)) -> Loja Rio de Janeiro | E13: =INDEX(Lojas!$E$2:$E$11,MATCH(C13,Lojas!$A$2:$A$11,0)) -> Sudeste
... A101: V100 | B101: Olívia Silva | C101: L10 | D101: =INDEX(Lojas!$B$2:$B$11,MATCH(C101,Lojas!$A$2:$A$11,0)) -> Loja Fortaleza | E101: =INDEX(Lojas!$E$2:$E$11,MATCH(C101,Lojas!$A$2:$A$11,0)) -> Nordeste

Sheet Produtos
A1: produto_id | B1: categoria | C1: modelo | D1: preco_unitario | E1: custo_unitario | F1: margem_unitaria | G1: margem_%
A2: P01 | B2: Notebook | C2: Lenovo | D2: 3199 | E2: 2350 | F2: =D2-E2 -> 849 | G2: =IFERROR(F2/D2,0) -> 0.26539544
A3: P02 | B3: Notebook | C3: Positivo | D3: 2199 | E3: 1550 | F3: =D3-E3 -> 649 | G3: =IFERROR(F3/D3,0) -> 0.29513415
A4: P03 | B4: Celular | C4: Samsung | D4: 2499 | E4: 1800 | F4: =D4-E4 -> 699 | G4: =IFERROR(F4/D4,0) -> 0.27971188
A5: P04 | B5: Celular | C5: Motorola | D5: 1799 | E5: 1250 | F5: =D5-E5 -> 549 | G5: =IFERROR(F5/D5,0) -> 0.30516954
A6: P05 | B6: Fone de Ouvido | C6: De Celular | D6: 59.9 | E6: 28 | F6: =D6-E6 -> 31.9 | G6: =IFERROR(F6/D6,0) -> 0.53255426
A7: P06 | B7: Fone de Ouvido | C7: Headset | D7: 249.9 | E7: 145 | F7: =D7-E7 -> 104.9 | G7: =IFERROR(F7/D7,0) -> 0.41976791
A8: P07 | B8: Carregador de Celular | C8: Tipo C | D8: 44.9 | E8: 18 | F8: =D8-E8 -> 26.9 | G8: =IFERROR(F8/D8,0) -> 0.59910913
A9: P08 | B9: Controle de Videogame | C9: Xbox | D9: 349.9 | E9: 215 | F9: =D9-E9 -> 134.9 | G9: =IFERROR(F9/D9,0) -> 0.38553873
A10: P09 | B10: Controle de Videogame | C10: PS4 | D10: 299.9 | E10: 175 | F10: =D10-E10 -> 124.9 | G10: =IFERROR(F10/D10,0) -> 0.41647216
A11: P10 | B11: Controle de Videogame | C11: PS5 | D11: 379.9 | E11: 235 | F11: =D11-E11 -> 144.9 | G11: =IFERROR(F11/D11,0) -> 0.38141616
A13: Preço e custo unitário são premissas de entrada (célula azul) definidas pela empresa.

Sheet Vendas
A1: venda_id | B1: data | C1: vendedor_id | D1: loja_id | E1: regiao | F1: produto_id | G1: produto | H1: quantidade | I1: preco_unitario | J1: valor_total | K1: custo_unitario | L1: custo_total
A2: VD00190 | B2: 46023 | C2: V097 | D2: =INDEX(Vendedores!$C$2:$C$101,MATCH(C2,Vendedores!$A$2:$A$101,0)) -> L10 | E2: =INDEX(Lojas!$E$2:$E$11,MATCH(D2,Lojas!$A$2:$A$11,0)) -> Nordeste | F2: P02 | G2: =INDEX(Produtos!$B$2:$B$11,MATCH(F2,Produtos!$A$2:$A$11,0))&" "&INDEX(Produtos!$C$2:$C$11,MATCH(F2,Produtos!$A$2:$A$11,0)) -> Notebook Positivo | H2: 1 | I2: =INDEX(Produtos!$D$2:$D$11,MATCH(F2,Produtos!$A$2:$A$11,0)) -> 2199 | J2: =H2*I2 -> 2199 | K2: =INDEX(Produtos!$E$2:$E$11,MATCH(F2,Produtos!$A$2:$A$11,0)) -> 1550 | L2: =H2*K2 -> 1550
A3: VD00711 | B3: 46023 | C3: V089 | D3: =INDEX(Vendedores!$C$2:$C$101,MATCH(C3,Vendedores!$A$2:$A$101,0)) -> L09 | E3: =INDEX(Lojas!$E$2:$E$11,MATCH(D3,Lojas!$A$2:$A$11,0)) -> Nordeste | F3: P04 | G3: =INDEX(Produtos!$B$2:$B$11,MATCH(F3,Produtos!$A$2:$A$11,0))&" "&INDEX(Produtos!$C$2:$C$11,MATCH(F3,Produtos!$A$2:$A$11,0)) -> Celular Motorola | H3: 2 | I3: =INDEX(Produtos!$D$2:$D$11,MATCH(F3,Produtos!$A$2:$A$11,0)) -> 1799 | J3: =H3*I3 -> 3598 | K3: =INDEX(Produtos!$E$2:$E$11,MATCH(F3,Produtos!$A$2:$A$11,0)) -> 1250 | L3: =H3*K3 -> 2500
A4: VD00719 | B4: 46023 | C4: V030 | D4: =INDEX(Vendedores!$C$2:$C$101,MATCH(C4,Vendedores!$A$2:$A$101,0)) -> L03 | E4: =INDEX(Lojas!$E$2:$E$11,MATCH(D4,Lojas!$A$2:$A$11,0)) -> Sudeste | F4: P04 | G4: =INDEX(Produtos!$B$2:$B$11,MATCH(F4,Produtos!$A$2:$A$11,0))&" "&INDEX(Produtos!$C$2:$C$11,MATCH(F4,Produtos!$A$2:$A$11,0)) -> Celular Motorola | H4: 3 | I4: =INDEX(Produtos!$D$2:$D$11,MATCH(F4,Produtos!$A$2:$A$11,0)) -> 1799 | J4: =H4*I4 -> 5397 | K4: =INDEX(Produtos!$E$2:$E$11,MATCH(F4,Produtos!$A$2:$A$11,0)) -> 1250 | L4: =H4*K4 -> 3750
A5: VD01338 | B5: 46023 | C5: V083 | D5: =INDEX(Vendedores!$C$2:$C$101,MATCH(C5,Vendedores!$A$2:$A$101,0)) -> L09 | E5: =INDEX(Lojas!$E$2:$E$11,MATCH(D5,Lojas!$A$2:$A$11,0)) -> Nordeste | F5: P07 | G5: =INDEX(Produtos!$B$2:$B$11,MATCH(F5,Produtos!$A$2:$A$11,0))&" "&INDEX(Produtos!$C$2:$C$11,MATCH(F5,Produtos!$A$2:$A$11,0)) -> Carregador de Celular Tipo C | H5: 2 | I5: =INDEX(Produtos!$D$2:$D$11,MATCH(F5,Produtos!$A$2:$A$11,0)) -> 44.9 | J5: =H5*I5 -> 89.8 | K5: =INDEX(Produtos!$E$2:$E$11,MATCH(F5,Produtos!$A$2:$A$11,0)) -> 18 | L5: =H5*K5 -> 36
A6: VD00767 | B6: 46023 | C6: V057 | D6: =INDEX(Vendedores!$C$2:$C$101,MATCH(C6,Vendedores!$A$2:$A$101,0)) -> L06 | E6: =INDEX(Lojas!$E$2:$E$11,MATCH(D6,Lojas!$A$2:$A$11,0)) -> Sul | F6: P05 | G6: =INDEX(Produtos!$B$2:$B$11,MATCH(F6,Produtos!$A$2:$A$11,0))&" "&INDEX(Produtos!$C$2:$C$11,MATCH(F6,Produtos!$A$2:$A$11,0)) -> Fone de Ouvido De Celular | H6: 1 | I6: =INDEX(Produtos!$D$2:$D$11,MATCH(F6,Produtos!$A$2:$A$11,0)) -> 59.9 | J6: =H6*I6 -> 59.9 | K6: =INDEX(Produtos!$E$2:$E$11,MATCH(F6,Produtos!$A$2:$A$11,0)) -> 28 | L6: =H6*K6 -> 28
A7: VD02085 | B7: 46023 | C7: V086 | D7: =INDEX(Vendedores!$C$2:$C$101,MATCH(C7,Vendedores!$A$2:$A$101,0)) -> L09 | E7: =INDEX(Lojas!$E$2:$E$11,MATCH(D7,Lojas!$A$2:$A$11,0)) -> Nordeste | F7: P10 | G7: =INDEX(Produtos!$B$2:$B$11,MATCH(F7,Produtos!$A$2:$A$11,0))&" "&INDEX(Produtos!$C$2:$C$11,MATCH(F7,Produtos!$A$2:$A$11,0)) -> Controle de Videogame PS5 | H7: 1 | I7: =INDEX(Produtos!$D$2:$D$11,MATCH(F7,Produtos!$A$2:$A$11,0)) -> 379.9 | J7: =H7*I7 -> 379.9 | K7: =INDEX(Produtos!$E$2:$E$11,MATCH(F7,Produtos!$A$2:$A$11,0)) -> 235 | L7: =H7*K7 -> 235
A8: VD00725 | B8: 46023 | C8: V007 | D8: =INDEX(Vendedores!$C$2:$C$101,MATCH(C8,Vendedores!$A$2:$A$101,0)) -> L01 | E8: =INDEX(Lojas!$E$2:$E$11,MATCH(D8,Lojas!$A$2:$A$11,0)) -> Sudeste | F8: P04 | G8: =INDEX(Produtos!$B$2:$B$11,MATCH(F8,Produtos!$A$2:$A$11,0))&" "&INDEX(Produtos!$C$2:$C$11,MATCH(F8,Produtos!$A$2:$A$11,0)) -> Celular Motorola | H8: 1 | I8: =INDEX(Produtos!$D$2:$D$11,MATCH(F8,Produtos!$A$2:$A$11,0)) -> 1799 | J8: =H8*I8 -> 1799 | K8: =INDEX(Produtos!$E$2:$E$11,MATCH(F8,Produtos!$A$2:$A$11,0)) -> 1250 | L8: =H8*K8 -> 1250
A9: VD00042 | B9: 46023 | C9: V072 | D9: =INDEX(Vendedores!$C$2:$C$101,MATCH(C9,Vendedores!$A$2:$A$101,0)) -> L08 | E9: =INDEX(Lojas!$E$2:$E$11,MATCH(D9,Lojas!$A$2:$A$11,0)) -> Nordeste | F9: P01 | G9: =INDEX(Produtos!$B$2:$B$11,MATCH(F9,Produtos!$A$2:$A$11,0))&" "&INDEX(Produtos!$C$2:$C$11,MATCH(F9,Produtos!$A$2:$A$11,0)) -> Notebook Lenovo | H9: 1 | I9: =INDEX(Produtos!$D$2:$D$11,MATCH(F9,Produtos!$A$2:$A$11,0)) -> 3199 | J9: =H9*I9 -> 3199 | K9: =INDEX(Produtos!$E$2:$E$11,MATCH(F9,Produtos!$A$2:$A$11,0)) -> 2350 | L9: =H9*K9 -> 2350
A10: VD00977 | B10: 46023 | C10: V048 | D10: =INDEX(Vendedores!$C$2:$C$101,MATCH(C10,Vendedores!$A$2:$A$101,0)) -> L05 | E10: =INDEX(Lojas!$E$2:$E$11,MATCH(D10,Lojas!$A$2:$A$11,0)) -> Sul | F10: P05 | G10: =INDEX(Produtos!$B$2:$B$11,MATCH(F10,Produtos!$A$2:$A$11,0))&" "&INDEX(Produtos!$C$2:$C$11,MATCH(F10,Produtos!$A$2:$A$11,0)) -> Fone de Ouvido De Celular | H10: 1 | I10: =INDEX(Produtos!$D$2:$D$11,MATCH(F10,Produtos!$A$2:$A$11,0)) -> 59.9 | J10: =H10*I10 -> 59.9 | K10: =INDEX(Produtos!$E$2:$E$11,MATCH(F10,Produtos!$A$2:$A$11,0)) -> 28 | L10: =H10*K10 -> 28
A11: VD00064 | B11: 46023 | C11: V028 | D11: =INDEX(Vendedores!$C$2:$C$101,MATCH(C11,Vendedores!$A$2:$A$101,0)) -> L03 | E11: =INDEX(Lojas!$E$2:$E$11,MATCH(D11,Lojas!$A$2:$A$11,0)) -> Sudeste | F11: P01 | G11: =INDEX(Produtos!$B$2:$B$11,MATCH(F11,Produtos!$A$2:$A$11,0))&" "&INDEX(Produtos!$C$2:$C$11,MATCH(F11,Produtos!$A$2:$A$11,0)) -> Notebook Lenovo | H11: 1 | I11: =INDEX(Produtos!$D$2:$D$11,MATCH(F11,Produtos!$A$2:$A$11,0)) -> 3199 | J11: =H11*I11 -> 3199 | K11: =INDEX(Produtos!$E$2:$E$11,MATCH(F11,Produtos!$A$2:$A$11,0)) -> 2350 | L11: =H11*K11 -> 2350
A12: VD01010 | B12: 46023 | C12: V036 | D12: =INDEX(Vendedores!$C$2:$C$101,MATCH(C12,Vendedores!$A$2:$A$101,0)) -> L04 | E12: =INDEX(Lojas!$E$2:$E$11,MATCH(D12,Lojas!$A$2:$A$11,0)) -> Sudeste | F12: P05 | G12: =INDEX(Produtos!$B$2:$B$11,MATCH(F12,Produtos!$A$2:$A$11,0))&" "&INDEX(Produtos!$C$2:$C$11,MATCH(F12,Produtos!$A$2:$A$11,0)) -> Fone de Ouvido De Celular | H12: 2 | I12: =INDEX(Produtos!$D$2:$D$11,MATCH(F12,Produtos!$A$2:$A$11,0)) -> 59.9 | J12: =H12*I12 -> 119.8 | K12: =INDEX(Produtos!$E$2:$E$11,MATCH(F12,Produtos!$A$2:$A$11,0)) -> 28 | L12: =H12*K12 -> 56
A13: VD01309 | B13: 46023 | C13: V085 | D13: =INDEX(Vendedores!$C$2:$C$101,MATCH(C13,Vendedores!$A$2:$A$101,0)) -> L09 | E13: =INDEX(Lojas!$E$2:$E$11,MATCH(D13,Lojas!$A$2:$A$11,0)) -> Nordeste | F13: P07 | G13: =INDEX(Produtos!$B$2:$B$11,MATCH(F13,Produtos!$A$2:$A$11,0))&" "&INDEX(Produtos!$C$2:$C$11,MATCH(F13,Produtos!$A$2:$A$11,0)) -> Carregador de Celular Tipo C | H13: 2 | I13: =INDEX(Produtos!$D$2:$D$11,MATCH(F13,Produtos!$A$2:$A$11,0)) -> 44.9 | J13: =H13*I13 -> 89.8 | K13: =INDEX(Produtos!$E$2:$E$11,MATCH(F13,Produtos!$A$2:$A$11,0)) -> 18 | L13: =H13*K13 -> 36
... A2181: VD01687 | B2181: 46203 | C2181: V046 | D2181: =INDEX(Vendedores!$C$2:$C$101,MATCH(C2181,Vendedores!$A$2:$A$101,0)) -> L05 | E2181: =INDEX(Lojas!$E$2:$E$11,MATCH(D2181,Lojas!$A$2:$A$11,0)) -> Sul | F2181: P08 | G2181: =INDEX(Produtos!$B$2:$B$11,MATCH(F2181,Produtos!$A$2:$A$11,0))&" "&INDEX(Produtos!$C$2:$C$11,MATCH(F2181,Produtos!$A$2:$A$11,0)) -> Controle de Videogame Xbox | H2181: 1 | I2181: =INDEX(Produtos!$D$2:$D$11,MATCH(F2181,Produtos!$A$2:$A$11,0)) -> 349.9 | J2181: =H2181*I2181 -> 349.9 | K2181: =INDEX(Produtos!$E$2:$E$11,MATCH(F2181,Produtos!$A$2:$A$11,0)) -> 215 | L2181: =H2181*K2181 -> 215

Sheet Desempenho_Vendedores
A1: vendedor_id | B1: nome_vendedor | C1: loja_id | D1: regiao | E1: numero_de_vendas | F1: valor_total_vendido | G1: ticket_medio
A2: V001 | B2: =INDEX(Vendedores!$B$2:$B$101,MATCH(A2,Vendedores!$A$2:$A$101,0)) -> Hugo Silva | C2: =INDEX(Vendedores!$C$2:$C$101,MATCH(A2,Vendedores!$A$2:$A$101,0)) -> L01 | D2: =INDEX(Vendedores!$E$2:$E$101,MATCH(A2,Vendedores!$A$2:$A$101,0)) -> Sudeste | E2: =COUNTIF(Vendas!$C$2:$C$2181,A2) -> 10 | F2: =SUMIF(Vendas!$C$2:$C$2181,A2,Vendas!$J$2:$J$2181) -> 18903.4 | G2: =IFERROR(F2/E2,0) -> 1890.34
A3: V002 | B3: =INDEX(Vendedores!$B$2:$B$101,MATCH(A3,Vendedores!$A$2:$A$101,0)) -> Rafael Almeida | C3: =INDEX(Vendedores!$C$2:$C$101,MATCH(A3,Vendedores!$A$2:$A$101,0)) -> L01 | D3: =INDEX(Vendedores!$E$2:$E$101,MATCH(A3,Vendedores!$A$2:$A$101,0)) -> Sudeste | E3: =COUNTIF(Vendas!$C$2:$C$2181,A3) -> 14 | F3: =SUMIF(Vendas!$C$2:$C$2181,A3,Vendas!$J$2:$J$2181) -> 31453.1 | G3: =IFERROR(F3/E3,0) -> 2246.65
A4: V003 | B4: =INDEX(Vendedores!$B$2:$B$101,MATCH(A4,Vendedores!$A$2:$A$101,0)) -> Olívia Pereira | C4: =INDEX(Vendedores!$C$2:$C$101,MATCH(A4,Vendedores!$A$2:$A$101,0)) -> L01 | D4: =INDEX(Vendedores!$E$2:$E$101,MATCH(A4,Vendedores!$A$2:$A$101,0)) -> Sudeste | E4: =COUNTIF(Vendas!$C$2:$C$2181,A4) -> 19 | F4: =SUMIF(Vendas!$C$2:$C$2181,A4,Vendas!$J$2:$J$2181) -> 33357.7 | G4: =IFERROR(F4/E4,0) -> 1755.6684
A5: V004 | B5: =INDEX(Vendedores!$B$2:$B$101,MATCH(A5,Vendedores!$A$2:$A$101,0)) -> Gabriela Alves | C5: =INDEX(Vendedores!$C$2:$C$101,MATCH(A5,Vendedores!$A$2:$A$101,0)) -> L01 | D5: =INDEX(Vendedores!$E$2:$E$101,MATCH(A5,Vendedores!$A$2:$A$101,0)) -> Sudeste | E5: =COUNTIF(Vendas!$C$2:$C$2181,A5) -> 10 | F5: =SUMIF(Vendas!$C$2:$C$2181,A5,Vendas!$J$2:$J$2181) -> 9121.9 | G5: =IFERROR(F5/E5,0) -> 912.19
A6: V005 | B6: =INDEX(Vendedores!$B$2:$B$101,MATCH(A6,Vendedores!$A$2:$A$101,0)) -> Fabio Monteiro | C6: =INDEX(Vendedores!$C$2:$C$101,MATCH(A6,Vendedores!$A$2:$A$101,0)) -> L01 | D6: =INDEX(Vendedores!$E$2:$E$101,MATCH(A6,Vendedores!$A$2:$A$101,0)) -> Sudeste | E6: =COUNTIF(Vendas!$C$2:$C$2181,A6) -> 9 | F6: =SUMIF(Vendas!$C$2:$C$2181,A6,Vendas!$J$2:$J$2181) -> 16984 | G6: =IFERROR(F6/E6,0) -> 1887.1111
A7: V006 | B7: =INDEX(Vendedores!$B$2:$B$101,MATCH(A7,Vendedores!$A$2:$A$101,0)) -> Bernardo Souza | C7: =INDEX(Vendedores!$C$2:$C$101,MATCH(A7,Vendedores!$A$2:$A$101,0)) -> L01 | D7: =INDEX(Vendedores!$E$2:$E$101,MATCH(A7,Vendedores!$A$2:$A$101,0)) -> Sudeste | E7: =COUNTIF(Vendas!$C$2:$C$2181,A7) -> 23 | F7: =SUMIF(Vendas!$C$2:$C$2181,A7,Vendas!$J$2:$J$2181) -> 39514.6 | G7: =IFERROR(F7/E7,0) -> 1718.0261
A8: V007 | B8: =INDEX(Vendedores!$B$2:$B$101,MATCH(A8,Vendedores!$A$2:$A$101,0)) -> Bruno Oliveira | C8: =INDEX(Vendedores!$C$2:$C$101,MATCH(A8,Vendedores!$A$2:$A$101,0)) -> L01 | D8: =INDEX(Vendedores!$E$2:$E$101,MATCH(A8,Vendedores!$A$2:$A$101,0)) -> Sudeste | E8: =COUNTIF(Vendas!$C$2:$C$2181,A8) -> 22 | F8: =SUMIF(Vendas!$C$2:$C$2181,A8,Vendas!$J$2:$J$2181) -> 33996.4 | G8: =IFERROR(F8/E8,0) -> 1545.2909
A9: V008 | B9: =INDEX(Vendedores!$B$2:$B$101,MATCH(A9,Vendedores!$A$2:$A$101,0)) -> Nelson Almeida | C9: =INDEX(Vendedores!$C$2:$C$101,MATCH(A9,Vendedores!$A$2:$A$101,0)) -> L01 | D9: =INDEX(Vendedores!$E$2:$E$101,MATCH(A9,Vendedores!$A$2:$A$101,0)) -> Sudeste | E9: =COUNTIF(Vendas!$C$2:$C$2181,A9) -> 13 | F9: =SUMIF(Vendas!$C$2:$C$2181,A9,Vendas!$J$2:$J$2181) -> 30587 | G9: =IFERROR(F9/E9,0) -> 2352.8462
A10: V009 | B10: =INDEX(Vendedores!$B$2:$B$101,MATCH(A10,Vendedores!$A$2:$A$101,0)) -> Giovana Barbosa | C10: =INDEX(Vendedores!$C$2:$C$101,MATCH(A10,Vendedores!$A$2:$A$101,0)) -> L01 | D10: =INDEX(Vendedores!$E$2:$E$101,MATCH(A10,Vendedores!$A$2:$A$101,0)) -> Sudeste | E10: =COUNTIF(Vendas!$C$2:$C$2181,A10) -> 17 | F10: =SUMIF(Vendas!$C$2:$C$2181,A10,Vendas!$J$2:$J$2181) -> 49349.2 | G10: =IFERROR(F10/E10,0) -> 2902.8941
A11: V010 | B11: =INDEX(Vendedores!$B$2:$B$101,MATCH(A11,Vendedores!$A$2:$A$101,0)) -> Bruno Alves | C11: =INDEX(Vendedores!$C$2:$C$101,MATCH(A11,Vendedores!$A$2:$A$101,0)) -> L01 | D11: =INDEX(Vendedores!$E$2:$E$101,MATCH(A11,Vendedores!$A$2:$A$101,0)) -> Sudeste | E11: =COUNTIF(Vendas!$C$2:$C$2181,A11) -> 20 | F11: =SUMIF(Vendas!$C$2:$C$2181,A11,Vendas!$J$2:$J$2181) -> 44013.7 | G11: =IFERROR(F11/E11,0) -> 2200.685
A12: V011 | B12: =INDEX(Vendedores!$B$2:$B$101,MATCH(A12,Vendedores!$A$2:$A$101,0)) -> Mariana Alves | C12: =INDEX(Vendedores!$C$2:$C$101,MATCH(A12,Vendedores!$A$2:$A$101,0)) -> L02 | D12: =INDEX(Vendedores!$E$2:$E$101,MATCH(A12,Vendedores!$A$2:$A$101,0)) -> Sudeste | E12: =COUNTIF(Vendas!$C$2:$C$2181,A12) -> 21 | F12: =SUMIF(Vendas!$C$2:$C$2181,A12,Vendas!$J$2:$J$2181) -> 34366.5 | G12: =IFERROR(F12/E12,0) -> 1636.5
A13: V012 | B13: =INDEX(Vendedores!$B$2:$B$101,MATCH(A13,Vendedores!$A$2:$A$101,0)) -> Aline Almeida | C13: =INDEX(Vendedores!$C$2:$C$101,MATCH(A13,Vendedores!$A$2:$A$101,0)) -> L02 | D13: =INDEX(Vendedores!$E$2:$E$101,MATCH(A13,Vendedores!$A$2:$A$101,0)) -> Sudeste | E13: =COUNTIF(Vendas!$C$2:$C$2181,A13) -> 12 | F13: =SUMIF(Vendas!$C$2:$C$2181,A13,Vendas!$J$2:$J$2181) -> 19193 | G13: =IFERROR(F13/E13,0) -> 1599.4167
... A101: V100 | B101: =INDEX(Vendedores!$B$2:$B$101,MATCH(A101,Vendedores!$A$2:$A$101,0)) -> Olívia Silva | C101: =INDEX(Vendedores!$C$2:$C$101,MATCH(A101,Vendedores!$A$2:$A$101,0)) -> L10 | D101: =INDEX(Vendedores!$E$2:$E$101,MATCH(A101,Vendedores!$A$2:$A$101,0)) -> Nordeste | E101: =COUNTIF(Vendas!$C$2:$C$2181,A101) -> 24 | F101: =SUMIF(Vendas!$C$2:$C$2181,A101,Vendas!$J$2:$J$2181) -> 46229.5 | G101: =IFERROR(F101/E101,0) -> 1926.2292

Sheet Resumo_Produto
A1: produto_id | B1: produto | C1: quantidade_vendida | D1: valor_total_vendido | E1: custo_total_alocacao | F1: lucro_total | G1: margem_% | H1: vendido_Sudeste | I1: vendido_Sul | J1: vendido_Nordeste | K1: regiao_que_mais_vendeu
A2: P01 | B2: =INDEX(Produtos!$B$2:$B$11,MATCH(A2,Produtos!$A$2:$A$11,0))&" "&INDEX(Produtos!$C$2:$C$11,MATCH(A2,Produtos!$A$2:$A$11,0)) -> Notebook Lenovo | C2: =SUMIF(Vendas!$F$2:$F$2181,A2,Vendas!$H$2:$H$2181) -> 212 | D2: =SUMIF(Vendas!$F$2:$F$2181,A2,Vendas!$J$2:$J$2181) -> 678188 | E2: =SUMIF(Vendas!$F$2:$F$2181,A2,Vendas!$L$2:$L$2181) -> 498200 | F2: =D2-E2 -> 179988 | G2: =IFERROR(F2/D2,0) -> 0.26539544 | H2: =SUMIFS(Vendas!$J$2:$J$2181,Vendas!$F$2:$F$2181,A2,Vendas!$E$2:$E$2181,"Sudeste") -> 415870 | I2: =SUMIFS(Vendas!$J$2:$J$2181,Vendas!$F$2:$F$2181,A2,Vendas!$E$2:$E$2181,"Sul") -> 131159 | J2: =SUMIFS(Vendas!$J$2:$J$2181,Vendas!$F$2:$F$2181,A2,Vendas!$E$2:$E$2181,"Nordeste") -> 131159 | K2: =INDEX({"Sudeste","Sul","Nordeste"},MATCH(MAX(H2:J2),H2:J2,0)) -> Sudeste
A3: P02 | B3: =INDEX(Produtos!$B$2:$B$11,MATCH(A3,Produtos!$A$2:$A$11,0))&" "&INDEX(Produtos!$C$2:$C$11,MATCH(A3,Produtos!$A$2:$A$11,0)) -> Notebook Positivo | C3: =SUMIF(Vendas!$F$2:$F$2181,A3,Vendas!$H$2:$H$2181) -> 288 | D3: =SUMIF(Vendas!$F$2:$F$2181,A3,Vendas!$J$2:$J$2181) -> 633312 | E3: =SUMIF(Vendas!$F$2:$F$2181,A3,Vendas!$L$2:$L$2181) -> 446400 | F3: =D3-E3 -> 186912 | G3: =IFERROR(F3/D3,0) -> 0.29513415 | H3: =SUMIFS(Vendas!$J$2:$J$2181,Vendas!$F$2:$F$2181,A3,Vendas!$E$2:$E$2181,"Sudeste") -> 114348 | I3: =SUMIFS(Vendas!$J$2:$J$2181,Vendas!$F$2:$F$2181,A3,Vendas!$E$2:$E$2181,"Sul") -> 142935 | J3: =SUMIFS(Vendas!$J$2:$J$2181,Vendas!$F$2:$F$2181,A3,Vendas!$E$2:$E$2181,"Nordeste") -> 376029 | K3: =INDEX({"Sudeste","Sul","Nordeste"},MATCH(MAX(H3:J3),H3:J3,0)) -> Nordeste
A4: P03 | B4: =INDEX(Produtos!$B$2:$B$11,MATCH(A4,Produtos!$A$2:$A$11,0))&" "&INDEX(Produtos!$C$2:$C$11,MATCH(A4,Produtos!$A$2:$A$11,0)) -> Celular Samsung | C4: =SUMIF(Vendas!$F$2:$F$2181,A4,Vendas!$H$2:$H$2181) -> 265 | D4: =SUMIF(Vendas!$F$2:$F$2181,A4,Vendas!$J$2:$J$2181) -> 662235 | E4: =SUMIF(Vendas!$F$2:$F$2181,A4,Vendas!$L$2:$L$2181) -> 477000 | F4: =D4-E4 -> 185235 | G4: =IFERROR(F4/D4,0) -> 0.27971188 | H4: =SUMIFS(Vendas!$J$2:$J$2181,Vendas!$F$2:$F$2181,A4,Vendas!$E$2:$E$2181,"Sudeste") -> 392343 | I4: =SUMIFS(Vendas!$J$2:$J$2181,Vendas!$F$2:$F$2181,A4,Vendas!$E$2:$E$2181,"Sul") -> 129948 | J4: =SUMIFS(Vendas!$J$2:$J$2181,Vendas!$F$2:$F$2181,A4,Vendas!$E$2:$E$2181,"Nordeste") -> 139944 | K4: =INDEX({"Sudeste","Sul","Nordeste"},MATCH(MAX(H4:J4),H4:J4,0)) -> Sudeste
A5: P04 | B5: =INDEX(Produtos!$B$2:$B$11,MATCH(A5,Produtos!$A$2:$A$11,0))&" "&INDEX(Produtos!$C$2:$C$11,MATCH(A5,Produtos!$A$2:$A$11,0)) -> Celular Motorola | C5: =SUMIF(Vendas!$F$2:$F$2181,A5,Vendas!$H$2:$H$2181) -> 276 | D5: =SUMIF(Vendas!$F$2:$F$2181,A5,Vendas!$J$2:$J$2181) -> 496524 | E5: =SUMIF(Vendas!$F$2:$F$2181,A5,Vendas!$L$2:$L$2181) -> 345000 | F5: =D5-E5 -> 151524 | G5: =IFERROR(F5/D5,0) -> 0.30516954 | H5: =SUMIFS(Vendas!$J$2:$J$2181,Vendas!$F$2:$F$2181,A5,Vendas!$E$2:$E$2181,"Sudeste") -> 111538 | I5: =SUMIFS(Vendas!$J$2:$J$2181,Vendas!$F$2:$F$2181,A5,Vendas!$E$2:$E$2181,"Sul") -> 113337 | J5: =SUMIFS(Vendas!$J$2:$J$2181,Vendas!$F$2:$F$2181,A5,Vendas!$E$2:$E$2181,"Nordeste") -> 271649 | K5: =INDEX({"Sudeste","Sul","Nordeste"},MATCH(MAX(H5:J5),H5:J5,0)) -> Nordeste
A6: P05 | B6: =INDEX(Produtos!$B$2:$B$11,MATCH(A6,Produtos!$A$2:$A$11,0))&" "&INDEX(Produtos!$C$2:$C$11,MATCH(A6,Produtos!$A$2:$A$11,0)) -> Fone de Ouvido De Celular | C6: =SUMIF(Vendas!$F$2:$F$2181,A6,Vendas!$H$2:$H$2181) -> 374 | D6: =SUMIF(Vendas!$F$2:$F$2181,A6,Vendas!$J$2:$J$2181) -> 22402.6 | E6: =SUMIF(Vendas!$F$2:$F$2181,A6,Vendas!$L$2:$L$2181) -> 10472 | F6: =D6-E6 -> 11930.6 | G6: =IFERROR(F6/D6,0) -> 0.53255426 | H6: =SUMIFS(Vendas!$J$2:$J$2181,Vendas!$F$2:$F$2181,A6,Vendas!$E$2:$E$2181,"Sudeste") -> 4971.7 | I6: =SUMIFS(Vendas!$J$2:$J$2181,Vendas!$F$2:$F$2181,A6,Vendas!$E$2:$E$2181,"Sul") -> 13118.1 | J6: =SUMIFS(Vendas!$J$2:$J$2181,Vendas!$F$2:$F$2181,A6,Vendas!$E$2:$E$2181,"Nordeste") -> 4312.8 | K6: =INDEX({"Sudeste","Sul","Nordeste"},MATCH(MAX(H6:J6),H6:J6,0)) -> Sul
A7: P06 | B7: =INDEX(Produtos!$B$2:$B$11,MATCH(A7,Produtos!$A$2:$A$11,0))&" "&INDEX(Produtos!$C$2:$C$11,MATCH(A7,Produtos!$A$2:$A$11,0)) -> Fone de Ouvido Headset | C7: =SUMIF(Vendas!$F$2:$F$2181,A7,Vendas!$H$2:$H$2181) -> 209 | D7: =SUMIF(Vendas!$F$2:$F$2181,A7,Vendas!$J$2:$J$2181) -> 52229.1 | E7: =SUMIF(Vendas!$F$2:$F$2181,A7,Vendas!$L$2:$L$2181) -> 30305 | F7: =D7-E7 -> 21924.1 | G7: =IFERROR(F7/D7,0) -> 0.41976791 | H7: =SUMIFS(Vendas!$J$2:$J$2181,Vendas!$F$2:$F$2181,A7,Vendas!$E$2:$E$2181,"Sudeste") -> 27239.1 | I7: =SUMIFS(Vendas!$J$2:$J$2181,Vendas!$F$2:$F$2181,A7,Vendas!$E$2:$E$2181,"Sul") -> 15493.8 | J7: =SUMIFS(Vendas!$J$2:$J$2181,Vendas!$F$2:$F$2181,A7,Vendas!$E$2:$E$2181,"Nordeste") -> 9496.2 | K7: =INDEX({"Sudeste","Sul","Nordeste"},MATCH(MAX(H7:J7),H7:J7,0)) -> Sudeste
A8: P07 | B8: =INDEX(Produtos!$B$2:$B$11,MATCH(A8,Produtos!$A$2:$A$11,0))&" "&INDEX(Produtos!$C$2:$C$11,MATCH(A8,Produtos!$A$2:$A$11,0)) -> Carregador de Celular Tipo C | C8: =SUMIF(Vendas!$F$2:$F$2181,A8,Vendas!$H$2:$H$2181) -> 435 | D8: =SUMIF(Vendas!$F$2:$F$2181,A8,Vendas!$J$2:$J$2181) -> 19531.5 | E8: =SUMIF(Vendas!$F$2:$F$2181,A8,Vendas!$L$2:$L$2181) -> 7830 | F8: =D8-E8 -> 11701.5 | G8: =IFERROR(F8/D8,0) -> 0.59910913 | H8: =SUMIFS(Vendas!$J$2:$J$2181,Vendas!$F$2:$F$2181,A8,Vendas!$E$2:$E$2181,"Sudeste") -> 3592 | I8: =SUMIFS(Vendas!$J$2:$J$2181,Vendas!$F$2:$F$2181,A8,Vendas!$E$2:$E$2181,"Sul") -> 4445.1 | J8: =SUMIFS(Vendas!$J$2:$J$2181,Vendas!$F$2:$F$2181,A8,Vendas!$E$2:$E$2181,"Nordeste") -> 11494.4 | K8: =INDEX({"Sudeste","Sul","Nordeste"},MATCH(MAX(H8:J8),H8:J8,0)) -> Nordeste
A9: P08 | B9: =INDEX(Produtos!$B$2:$B$11,MATCH(A9,Produtos!$A$2:$A$11,0))&" "&INDEX(Produtos!$C$2:$C$11,MATCH(A9,Produtos!$A$2:$A$11,0)) -> Controle de Videogame Xbox | C9: =SUMIF(Vendas!$F$2:$F$2181,A9,Vendas!$H$2:$H$2181) -> 280 | D9: =SUMIF(Vendas!$F$2:$F$2181,A9,Vendas!$J$2:$J$2181) -> 97972 | E9: =SUMIF(Vendas!$F$2:$F$2181,A9,Vendas!$L$2:$L$2181) -> 60200 | F9: =D9-E9 -> 37772 | G9: =IFERROR(F9/D9,0) -> 0.38553873 | H9: =SUMIFS(Vendas!$J$2:$J$2181,Vendas!$F$2:$F$2181,A9,Vendas!$E$2:$E$2181,"Sudeste") -> 21693.8 | I9: =SUMIFS(Vendas!$J$2:$J$2181,Vendas!$F$2:$F$2181,A9,Vendas!$E$2:$E$2181,"Sul") -> 58433.3 | J9: =SUMIFS(Vendas!$J$2:$J$2181,Vendas!$F$2:$F$2181,A9,Vendas!$E$2:$E$2181,"Nordeste") -> 17844.9 | K9: =INDEX({"Sudeste","Sul","Nordeste"},MATCH(MAX(H9:J9),H9:J9,0)) -> Sul
A10: P09 | B10: =INDEX(Produtos!$B$2:$B$11,MATCH(A10,Produtos!$A$2:$A$11,0))&" "&INDEX(Produtos!$C$2:$C$11,MATCH(A10,Produtos!$A$2:$A$11,0)) -> Controle de Videogame PS4 | C10: =SUMIF(Vendas!$F$2:$F$2181,A10,Vendas!$H$2:$H$2181) -> 293 | D10: =SUMIF(Vendas!$F$2:$F$2181,A10,Vendas!$J$2:$J$2181) -> 87870.7 | E10: =SUMIF(Vendas!$F$2:$F$2181,A10,Vendas!$L$2:$L$2181) -> 51275 | F10: =D10-E10 -> 36595.7 | G10: =IFERROR(F10/D10,0) -> 0.41647216 | H10: =SUMIFS(Vendas!$J$2:$J$2181,Vendas!$F$2:$F$2181,A10,Vendas!$E$2:$E$2181,"Sudeste") -> 51582.8 | I10: =SUMIFS(Vendas!$J$2:$J$2181,Vendas!$F$2:$F$2181,A10,Vendas!$E$2:$E$2181,"Sul") -> 14395.2 | J10: =SUMIFS(Vendas!$J$2:$J$2181,Vendas!$F$2:$F$2181,A10,Vendas!$E$2:$E$2181,"Nordeste") -> 21892.7 | K10: =INDEX({"Sudeste","Sul","Nordeste"},MATCH(MAX(H10:J10),H10:J10,0)) -> Sudeste
A11: P10 | B11: =INDEX(Produtos!$B$2:$B$11,MATCH(A11,Produtos!$A$2:$A$11,0))&" "&INDEX(Produtos!$C$2:$C$11,MATCH(A11,Produtos!$A$2:$A$11,0)) -> Controle de Videogame PS5 | C11: =SUMIF(Vendas!$F$2:$F$2181,A11,Vendas!$H$2:$H$2181) -> 325 | D11: =SUMIF(Vendas!$F$2:$F$2181,A11,Vendas!$J$2:$J$2181) -> 123467.5 | E11: =SUMIF(Vendas!$F$2:$F$2181,A11,Vendas!$L$2:$L$2181) -> 76375 | F11: =D11-E11 -> 47092.5 | G11: =IFERROR(F11/D11,0) -> 0.38141616 | H11: =SUMIFS(Vendas!$J$2:$J$2181,Vendas!$F$2:$F$2181,A11,Vendas!$E$2:$E$2181,"Sudeste") -> 27732.7 | I11: =SUMIFS(Vendas!$J$2:$J$2181,Vendas!$F$2:$F$2181,A11,Vendas!$E$2:$E$2181,"Sul") -> 70281.5 | J11: =SUMIFS(Vendas!$J$2:$J$2181,Vendas!$F$2:$F$2181,A11,Vendas!$E$2:$E$2181,"Nordeste") -> 25453.3 | K11: =INDEX({"Sudeste","Sul","Nordeste"},MATCH(MAX(H11:J11),H11:J11,0)) -> Sul
A12: TOTAL | C12: =SUM(C2:C11) -> 2957 | D12: =SUM(D2:D11) -> 2873732.4 | E12: =SUM(E2:E11) -> 2003057 | F12: =SUM(F2:F11) -> 870675.4 | G12: =IFERROR(F12/D12,0) -> 0.3029772
A14: Período analisado: 01/01/2026 a 30/06/2026 (último semestre). Valores em R$.
